.gitignore
LICENSE
README.md
setup.py
guate/__init__.py
guate.division_politica.egg-info/PKG-INFO
guate.division_politica.egg-info/SOURCES.txt
guate.division_politica.egg-info/dependency_links.txt
guate.division_politica.egg-info/requires.txt
guate.division_politica.egg-info/top_level.txt
guate/division_politica/__init__.py
guate/division_politica/data.json
guate/division_politica/models.py
guate/division_politica/resources.py
guate/division_politica/migrations/0001-inicializacion/backward.sql
guate/division_politica/migrations/0001-inicializacion/forward.sql
guate/division_politica/migrations/0002-region/backward.sql
guate/division_politica/migrations/0002-region/forward.sql
tests/test_division_politica.py