Metadata-Version: 1.0
Name: guate.division-politica
Version: 0.2.1
Summary: División Política de Guatemala
Home-page: UNKNOWN
Author: Darwin Monroy
Author-email: contact@darwinmonroy.com
License: UNKNOWN
Platform: UNKNOWN
